jsonify.py
JSONifier-0.0.7.dist-info/LICENSE.txt
JSONifier-0.0.7.dist-info/METADATA
JSONifier-0.0.7.dist-info/WHEEL
JSONifier-0.0.7.dist-info/top_level.txt
JSONifier-0.0.7.dist-info/RECORD
