Metadata-Version: 2.1
Name: JSONifier
Version: 0.0.7
Summary: A package for reading, writing, and editing of JSON files, Python dictionaries, and such.
Home-page: https://github.com/MasterCoder21/JSONifier
Author: minecraftpr03
License: UNKNOWN
Platform: UNKNOWN
Classifier: Programming Language :: Python :: 3
Classifier: Programming Language :: Python :: 3.6
Classifier: Programming Language :: Python :: 3.7
Classifier: Programming Language :: Python :: 3.8
Classifier: Programming Language :: Python :: 3.9
Classifier: License :: OSI Approved :: MIT License
Classifier: Operating System :: OS Independent
